semantix_agentix/__init__.py
semantix_agentix/agentix.py
semantix_agentix/experiment_interceptor.py
semantix_agentix/metric_interceptor.py
semantix_agentix/model_interceptor.py
semantix_agentix/run_interceptor.py
semantix_agentix-0.1.10.dist-info/licenses/LICENSE
semantix_agentix-0.1.10.dist-info/METADATA
semantix_agentix-0.1.10.dist-info/WHEEL
semantix_agentix-0.1.10.dist-info/top_level.txt
semantix_agentix-0.1.10.dist-info/RECORD
