Metadata-Version: 2.4
Name: semantix-agentix
Version: 0.1.10
Summary: A Python library for AI governance and experiment tracking that integrates with MLflow
Author: Artur Rodrigues
Author-email: Artur Rodrigues <artur.rodrigues@semantix.ai>
License: MIT
Classifier: Development Status :: 4 - Beta
Classifier: Intended Audience :: Developers
Classifier: License :: OSI Approved :: MIT License
Classifier: Operating System :: OS Independent
Classifier: Programming Language :: Python :: 3
Classifier: Programming Language :: Python :: 3.10
Classifier: Programming Language :: Python :: 3.11
Classifier: Programming Language :: Python :: 3.12
Requires-Python: >=3.10
License-File: LICENSE
Requires-Dist: mlflow>=3.3.1
Requires-Dist: psycopg2-binary>=2.9.10
Dynamic: author
Dynamic: license-file
Dynamic: requires-python
